{
  "hash": "92ee28e9",
  "configHash": "12691d76",
  "lockfileHash": "c9d571a3",
  "browserHash": "93784a4c",
  "optimized": {
    "vue": {
      "src": "../../../node_modules/vue/dist/vue.runtime.esm-bundler.js",
      "file": "vue.js",
      "fileHash": "96e24833",
      "needsInterop": false
    },
    "vitepress > @vue/devtools-api": {
      "src": "../../../node_modules/@vue/devtools-api/lib/esm/index.js",
      "file": "vitepress___@vue_devtools-api.js",
      "fileHash": "3b6d6f97",
      "needsInterop": false
    },
    "vitepress > @vueuse/core": {
      "src": "../../../node_modules/@vueuse/core/index.mjs",
      "file": "vitepress___@vueuse_core.js",
      "fileHash": "6f4db284",
      "needsInterop": false
    },
    "vitepress > @vueuse/integrations/useFocusTrap": {
      "src": "../../../node_modules/@vueuse/integrations/useFocusTrap.mjs",
      "file": "vitepress___@vueuse_integrations_useFocusTrap.js",
      "fileHash": "023def2e",
      "needsInterop": false
    },
    "vitepress > mark.js/src/vanilla.js": {
      "src": "../../../node_modules/mark.js/src/vanilla.js",
      "file": "vitepress___mark__js_src_vanilla__js.js",
      "fileHash": "50d61895",
      "needsInterop": false
    },
    "vitepress > minisearch": {
      "src": "../../../node_modules/minisearch/dist/es/index.js",
      "file": "vitepress___minisearch.js",
      "fileHash": "4fdd6b05",
      "needsInterop": false
    },
    "vitepress-plugin-tabs/client": {
      "src": "../../../node_modules/vitepress-plugin-tabs/src/client/index.ts",
      "file": "vitepress-plugin-tabs_client.js",
      "fileHash": "27adc50b",
      "needsInterop": false
    }
  },
  "chunks": {
    "chunk-IM4JLXM5": {
      "file": "chunk-IM4JLXM5.js"
    },
    "chunk-I27O6UFQ": {
      "file": "chunk-I27O6UFQ.js"
    }
  }
}